ep_logging.py
ep_logging/__init__.py
micropython_eydam_prototyping_logging-0.0.7.dist-info/LICENSE
micropython_eydam_prototyping_logging-0.0.7.dist-info/METADATA
micropython_eydam_prototyping_logging-0.0.7.dist-info/WHEEL
micropython_eydam_prototyping_logging-0.0.7.dist-info/top_level.txt
micropython_eydam_prototyping_logging-0.0.7.dist-info/RECORD
